poliprompt/__init__.py
poliprompt/llm_contribs.py
poliprompt/reducers.py
poliprompt/retrieves.py
poliprompt/selectors.py
poliprompt/text_classifier.py
poliprompt/utils.py
PoliPrompt-0.2.1.dist-info/LICENSE
PoliPrompt-0.2.1.dist-info/METADATA
PoliPrompt-0.2.1.dist-info/WHEEL
PoliPrompt-0.2.1.dist-info/top_level.txt
PoliPrompt-0.2.1.dist-info/RECORD
